{
	"$schema": "http://schema.management.azure.com/schemas/2015-01-01/deploymentTemplate.json#",
	"contentVersion": "1.0.0.0",
	"parameters": {
		"factoryName": {
			"type": "string",
			"metadata": "Data Factory name",
			"defaultValue": "nickadf"
		},
		"AzureFileStorage1_connectionString": {
			"type": "secureString",
			"metadata": "Secure string for 'connectionString' of 'AzureFileStorage1'"
		},
		"AzureSynapseAnalytics2_connectionString": {
			"type": "secureString",
			"metadata": "Secure string for 'connectionString' of 'AzureSynapseAnalytics2'"
		},
		"LakeLinkedService_accountKey": {
			"type": "secureString",
			"metadata": "Secure string for 'accountKey' of 'LakeLinkedService'"
		},
		"linkedServiceForCSV_connectionString": {
			"type": "secureString",
			"metadata": "Secure string for 'connectionString' of 'linkedServiceForCSV'"
		},
		"OriiginCSVLinked_connectionString": {
			"type": "secureString",
			"metadata": "Secure string for 'connectionString' of 'OriiginCSVLinked'"
		},
		"LakeLinkedService_properties_typeProperties_url": {
			"type": "string",
			"defaultValue": "https://firstsan.dfs.core.windows.net"
		}
	},
	"variables": {
		"factoryId": "[concat('Microsoft.DataFactory/factories/', parameters('factoryName'))]"
	},
	"resources": [
		{
			"name": "[concat(parameters('factoryName'), '/pipeline1')]",
			"type": "Microsoft.DataFactory/factories/pipelines",
			"apiVersion": "2018-06-01",
			"properties": {
				"activities": [
					{
						"name": "DataFlow",
						"type": "ExecuteDataFlow",
						"dependsOn": [
							{
								"activity": "CopyData",
								"dependencyConditions": [
									"Succeeded"
								]
							}
						],
						"policy": {
							"timeout": "1.00:00:00",
							"retry": 0,
							"retryIntervalInSeconds": 30,
							"secureOutput": false,
							"secureInput": false
						},
						"userProperties": [],
						"typeProperties": {
							"dataflow": {
								"referenceName": "dataflow1",
								"type": "DataFlowReference",
								"parameters": {},
								"datasetParameters": {
									"dataFlowCSV": {},
									"sink1": {}
								}
							},
							"staging": {
								"linkedService": {
									"referenceName": "linkedServiceForCSV",
									"type": "LinkedServiceReference"
								},
								"folderPath": "nickcontainer/dw-test"
							},
							"compute": {
								"coreCount": 8,
								"computeType": "General"
							},
							"traceLevel": "Fine"
						}
					},
					{
						"name": "CopyData",
						"type": "Copy",
						"dependsOn": [],
						"policy": {
							"timeout": "7.00:00:00",
							"retry": 0,
							"retryIntervalInSeconds": 30,
							"secureOutput": false,
							"secureInput": false
						},
						"userProperties": [],
						"typeProperties": {
							"source": {
								"type": "DelimitedTextSource",
								"storeSettings": {
									"type": "AzureBlobStorageReadSettings",
									"recursive": true,
									"enablePartitionDiscovery": false
								},
								"formatSettings": {
									"type": "DelimitedTextReadSettings"
								}
							},
							"sink": {
								"type": "DelimitedTextSink",
								"storeSettings": {
									"type": "AzureBlobFSWriteSettings",
									"copyBehavior": {
										"value": "@pipeline().RunId",
										"type": "Expression"
									}
								},
								"formatSettings": {
									"type": "DelimitedTextWriteSettings",
									"quoteAllText": true,
									"fileExtension": ""
								}
							},
							"enableStaging": false,
							"translator": {
								"type": "TabularTranslator",
								"typeConversion": true,
								"typeConversionSettings": {
									"allowDataTruncation": true,
									"treatBooleanAsNumber": false
								}
							}
						},
						"inputs": [
							{
								"referenceName": "originCSV",
								"type": "DatasetReference",
								"parameters": {}
							}
						],
						"outputs": [
							{
								"referenceName": "lakeTransted",
								"type": "DatasetReference",
								"parameters": {}
							}
						]
					}
				],
				"policy": {
					"elapsedTimeMetric": {},
					"cancelAfter": {}
				},
				"annotations": []
			},
			"dependsOn": [
				"[concat(variables('factoryId'), '/dataflows/dataflow1')]",
				"[concat(variables('factoryId'), '/linkedServices/linkedServiceForCSV')]",
				"[concat(variables('factoryId'), '/datasets/originCSV')]",
				"[concat(variables('factoryId'), '/datasets/lakeTransted')]"
			]
		},
		{
			"name": "[concat(parameters('factoryName'), '/AzureSynapseAnalyticsTable1')]",
			"type": "Microsoft.DataFactory/factories/datasets",
			"apiVersion": "2018-06-01",
			"properties": {
				"linkedServiceName": {
					"referenceName": "AzureSynapseAnalytics2",
					"type": "LinkedServiceReference"
				},
				"annotations": [],
				"type": "AzureSqlDWTable",
				"schema": [],
				"typeProperties": {
					"schema": "dbo",
					"table": "Products"
				}
			},
			"dependsOn": [
				"[concat(variables('factoryId'), '/linkedServices/AzureSynapseAnalytics2')]"
			]
		},
		{
			"name": "[concat(parameters('factoryName'), '/DelimitedForCSV')]",
			"type": "Microsoft.DataFactory/factories/datasets",
			"apiVersion": "2018-06-01",
			"properties": {
				"linkedServiceName": {
					"referenceName": "linkedServiceForCSV",
					"type": "LinkedServiceReference"
				},
				"annotations": [],
				"type": "DelimitedText",
				"typeProperties": {
					"location": {
						"type": "AzureBlobStorageLocation",
						"fileName": "Sample-Spreadsheet-50000-rows.csv",
						"folderPath": "output",
						"container": "nickcontainer"
					},
					"columnDelimiter": ",",
					"escapeChar": "\\",
					"firstRowAsHeader": false,
					"quoteChar": "\""
				},
				"schema": [
					{
						"name": "Eldon Base for stackable storage shelf, platinum",
						"type": "String"
					},
					{
						"name": "Muhammed MacIntyre",
						"type": "String"
					},
					{
						"name": "3",
						"type": "String"
					},
					{
						"name": "-213.25",
						"type": "String"
					},
					{
						"name": "38.94",
						"type": "String"
					},
					{
						"name": "35",
						"type": "String"
					},
					{
						"name": "Nunavut",
						"type": "String"
					},
					{
						"name": "Storage & Organization",
						"type": "String"
					},
					{
						"name": "0.8",
						"type": "String"
					}
				]
			},
			"dependsOn": [
				"[concat(variables('factoryId'), '/linkedServices/linkedServiceForCSV')]"
			]
		},
		{
			"name": "[concat(parameters('factoryName'), '/lakeTransted')]",
			"type": "Microsoft.DataFactory/factories/datasets",
			"apiVersion": "2018-06-01",
			"properties": {
				"linkedServiceName": {
					"referenceName": "LakeLinkedService",
					"type": "LinkedServiceReference"
				},
				"annotations": [],
				"type": "DelimitedText",
				"typeProperties": {
					"location": {
						"type": "AzureBlobFSLocation",
						"folderPath": {
							"value": "output",
							"type": "Expression"
						},
						"fileSystem": "nickcontainer"
					},
					"columnDelimiter": ",",
					"escapeChar": "\\",
					"quoteChar": "\""
				},
				"schema": [
					{
						"type": "String"
					},
					{
						"type": "String"
					},
					{
						"type": "String"
					},
					{
						"type": "String"
					},
					{
						"type": "String"
					},
					{
						"type": "String"
					},
					{
						"type": "String"
					},
					{
						"type": "String"
					},
					{
						"type": "String"
					}
				]
			},
			"dependsOn": [
				"[concat(variables('factoryId'), '/linkedServices/LakeLinkedService')]"
			]
		},
		{
			"name": "[concat(parameters('factoryName'), '/AzureFileStorage1')]",
			"type": "Microsoft.DataFactory/factories/linkedServices",
			"apiVersion": "2018-06-01",
			"properties": {
				"annotations": [],
				"type": "AzureFileStorage",
				"typeProperties": {
					"connectionString": "[parameters('AzureFileStorage1_connectionString')]",
					"fileShare": "nick"
				}
			},
			"dependsOn": []
		},
		{
			"name": "[concat(parameters('factoryName'), '/AzureSynapseAnalytics2')]",
			"type": "Microsoft.DataFactory/factories/linkedServices",
			"apiVersion": "2018-06-01",
			"properties": {
				"annotations": [],
				"type": "AzureSqlDW",
				"typeProperties": {
					"connectionString": "[parameters('AzureSynapseAnalytics2_connectionString')]"
				}
			},
			"dependsOn": []
		},
		{
			"name": "[concat(parameters('factoryName'), '/LakeLinkedService')]",
			"type": "Microsoft.DataFactory/factories/linkedServices",
			"apiVersion": "2018-06-01",
			"properties": {
				"annotations": [],
				"type": "AzureBlobFS",
				"typeProperties": {
					"url": "[parameters('LakeLinkedService_properties_typeProperties_url')]",
					"accountKey": {
						"type": "SecureString",
						"value": "[parameters('LakeLinkedService_accountKey')]"
					}
				}
			},
			"dependsOn": []
		},
		{
			"name": "[concat(parameters('factoryName'), '/linkedServiceForCSV')]",
			"type": "Microsoft.DataFactory/factories/linkedServices",
			"apiVersion": "2018-06-01",
			"properties": {
				"annotations": [],
				"type": "AzureBlobStorage",
				"typeProperties": {
					"connectionString": "[parameters('linkedServiceForCSV_connectionString')]"
				}
			},
			"dependsOn": []
		},
		{
			"name": "[concat(parameters('factoryName'), '/integrationRuntime11')]",
			"type": "Microsoft.DataFactory/factories/integrationRuntimes",
			"apiVersion": "2018-06-01",
			"properties": {
				"type": "SelfHosted",
				"typeProperties": {}
			},
			"dependsOn": []
		},
		{
			"name": "[concat(parameters('factoryName'), '/integrationRuntime12')]",
			"type": "Microsoft.DataFactory/factories/integrationRuntimes",
			"apiVersion": "2018-06-01",
			"properties": {
				"type": "Managed",
				"typeProperties": {
					"computeProperties": {
						"location": "AutoResolve",
						"dataFlowProperties": {
							"computeType": "General",
							"coreCount": 8,
							"timeToLive": 10,
							"cleanup": false
						}
					}
				}
			},
			"dependsOn": []
		},
		{
			"name": "[concat(parameters('factoryName'), '/dataflow1')]",
			"type": "Microsoft.DataFactory/factories/dataflows",
			"apiVersion": "2018-06-01",
			"properties": {
				"type": "MappingDataFlow",
				"typeProperties": {
					"sources": [
						{
							"dataset": {
								"referenceName": "DelimitedForCSV",
								"type": "DatasetReference"
							},
							"name": "dataFlowCSV"
						}
					],
					"sinks": [
						{
							"dataset": {
								"referenceName": "AzureSynapseAnalyticsTable1",
								"type": "DatasetReference"
							},
							"name": "sink1"
						}
					],
					"transformations": [
						{
							"name": "Select1"
						},
						{
							"name": "AlterRow1"
						}
					],
					"script": "source(output(\n\t\t{Eldon Base for stackable storage shelf, platinum} as string,\n\t\t{Muhammed MacIntyre} as string,\n\t\t{3} as string,\n\t\t{-213.25} as string,\n\t\t{38.94} as string,\n\t\t{35} as string,\n\t\tNunavut as string,\n\t\t{Storage & Organization} as string,\n\t\t{0.8} as string\n\t),\n\tallowSchemaDrift: true,\n\tvalidateSchema: false,\n\tignoreNoFilesFound: false) ~> dataFlowCSV\ndataFlowCSV select(mapColumn(\n\t\ttitle = {Eldon Base for stackable storage shelf, platinum},\n\t\tname = {Muhammed MacIntyre},\n\t\tnum = {3},\n\t\tprice = {38.94},\n\t\tage = {35},\n\t\tlocation = Nunavut,\n\t\tcompay = {Storage & Organization},\n\t\tdoub = {0.8}\n\t),\n\tskipDuplicateMapInputs: true,\n\tskipDuplicateMapOutputs: true) ~> Select1\nSelect1 alterRow(updateIf(true())) ~> AlterRow1\nAlterRow1 sink(allowSchemaDrift: true,\n\tvalidateSchema: false,\n\tdeletable:false,\n\tinsertable:true,\n\tupdateable:false,\n\tupsertable:true,\n\tkeys:['name1'],\n\tformat: 'table',\n\tstaged: true,\n\tallowCopyCommand: true,\n\tskipDuplicateMapInputs: true,\n\tskipDuplicateMapOutputs: true,\n\terrorHandlingOption: 'stopOnFirstError',\n\tmapColumn(\n\t\tname1 = name,\n\t\tprice,\n\t\tage,\n\t\tlocation1 = location,\n\t\tdoub\n\t)) ~> sink1"
				}
			},
			"dependsOn": [
				"[concat(variables('factoryId'), '/datasets/DelimitedForCSV')]",
				"[concat(variables('factoryId'), '/datasets/AzureSynapseAnalyticsTable1')]"
			]
		},
		{
			"name": "[concat(parameters('factoryName'), '/OriiginCSVLinked')]",
			"type": "Microsoft.DataFactory/factories/linkedServices",
			"apiVersion": "2018-06-01",
			"properties": {
				"annotations": [],
				"type": "AzureBlobStorage",
				"typeProperties": {
					"connectionString": "[parameters('OriiginCSVLinked_connectionString')]"
				}
			},
			"dependsOn": []
		},
		{
			"name": "[concat(parameters('factoryName'), '/originCSV')]",
			"type": "Microsoft.DataFactory/factories/datasets",
			"apiVersion": "2018-06-01",
			"properties": {
				"linkedServiceName": {
					"referenceName": "OriiginCSVLinked",
					"type": "LinkedServiceReference"
				},
				"annotations": [],
				"type": "DelimitedText",
				"typeProperties": {
					"location": {
						"type": "AzureBlobStorageLocation",
						"fileName": "Sample-Spreadsheet-50000-rows.csv",
						"container": "nickcontainer"
					},
					"columnDelimiter": ",",
					"escapeChar": "\\",
					"quoteChar": "\""
				},
				"schema": [
					{
						"type": "String"
					},
					{
						"type": "String"
					},
					{
						"type": "String"
					},
					{
						"type": "String"
					},
					{
						"type": "String"
					},
					{
						"type": "String"
					},
					{
						"type": "String"
					},
					{
						"type": "String"
					},
					{
						"type": "String"
					}
				]
			},
			"dependsOn": [
				"[concat(variables('factoryId'), '/linkedServices/OriiginCSVLinked')]"
			]
		}
	]
}